frolicapp/__init__.py
frolicapp/cli.py
frolicapp/models.py
frolicapp/rbac.py
frolicapp/blueprints/admin/__init__.py
frolicapp/blueprints/admin/forms.py
frolicapp/blueprints/admin/static/assets/css/style.css
frolicapp/blueprints/admin/static/assets/img/darshan-frolic.png
frolicapp/blueprints/admin/static/assets/img/not-found.svg
frolicapp/blueprints/admin/static/assets/img/favicons/android-chrome-192x192.png
frolicapp/blueprints/admin/static/assets/img/favicons/android-chrome-512x512.png
frolicapp/blueprints/admin/static/assets/img/favicons/favicon-16x16.png
frolicapp/blueprints/admin/static/assets/img/favicons/favicon-32x32.png
frolicapp/blueprints/admin/static/assets/img/favicons/favicon.ico
frolicapp/blueprints/admin/static/assets/img/touch-icons/apple-touch-icon-ipad-76x76.png
frolicapp/blueprints/admin/static/assets/img/touch-icons/apple-touch-icon-ipad-retina-152x152.png
frolicapp/blueprints/admin/static/assets/img/touch-icons/apple-touch-icon-iphone-60x60.png
frolicapp/blueprints/admin/static/assets/img/touch-icons/apple-touch-icon-iphone-retina-120x120.png
frolicapp/blueprints/admin/static/assets/js/main.js
frolicapp/blueprints/admin/static/assets/vendor/bootstrap/css/bootstrap-grid.css
frolicapp/blueprints/admin/static/assets/vendor/bootstrap/css/bootstrap-grid.css.map
frolicapp/blueprints/admin/static/assets/vendor/bootstrap/css/bootstrap-grid.min.css
frolicapp/blueprints/admin/static/assets/vendor/bootstrap/css/bootstrap-grid.min.css.map
frolicapp/blueprints/admin/static/assets/vendor/bootstrap/css/bootstrap-grid.rtl.css
frolicapp/blueprints/admin/static/assets/vendor/bootstrap/css/bootstrap-grid.rtl.css.map
frolicapp/blueprints/admin/static/assets/vendor/bootstrap/css/bootstrap-grid.rtl.min.css
frolicapp/blueprints/admin/static/assets/vendor/bootstrap/css/bootstrap-grid.rtl.min.css.map
frolicapp/blueprints/admin/static/assets/vendor/bootstrap/css/bootstrap-reboot.css
frolicapp/blueprints/admin/static/assets/vendor/bootstrap/css/bootstrap-reboot.css.map
frolic_webserver-1.0.2.dist-info/METADATA
frolic_webserver-1.0.2.dist-info/WHEEL
frolic_webserver-1.0.2.dist-info/entry_points.txt
frolic_webserver-1.0.2.dist-info/top_level.txt
frolic_webserver-1.0.2.dist-info/RECORD
