Metadata-Version: 2.1
Name: frolic_webserver
Version: 1.0.2
Summary: An event management system made with Flask.
Author-email: Soham Jobanputra <sohamjobanputra7@gmail.com>
Project-URL: Repository, https://github.com/Soham7777777/Frolic2025
Requires-Python: >=3.12
Requires-Dist: Flask==3.0.3
Requires-Dist: python-dotenv==1.0.1
Requires-Dist: pydantic==2.9.2
Requires-Dist: mypy==1.13.0
Requires-Dist: Flask-SQLAlchemy==3.1.1
Requires-Dist: email_validator==2.2.0
Requires-Dist: Faker==30.8.2
Requires-Dist: nh3==0.2.18
Requires-Dist: Flask-WTF==1.2.2
